PRF/__init__.py
PRF/prf.py
TESS_PRF/__init__.py
TESS_PRF-0.1.0.dist-info/LICENSE
TESS_PRF-0.1.0.dist-info/METADATA
TESS_PRF-0.1.0.dist-info/WHEEL
TESS_PRF-0.1.0.dist-info/top_level.txt
TESS_PRF-0.1.0.dist-info/RECORD
