Metadata-Version: 2.1
Name: TESS-PRF
Version: 0.1.0
Summary: Tools to display the TESS pixel response function (PRF) at any location on the detector
Home-page: https://github.com/keatonb/TESS_PRF
Author: Keaton Bell
Author-email: keatonbell@utexas.edu
License: UNKNOWN
Project-URL: Bug Tracker, https://github.com/keatonb/TESS_PRF/issues
Platform: UNKNOWN
Classifier: Programming Language :: Python :: 3
Classifier: License :: OSI Approved :: MIT License
Classifier: Operating System :: OS Independent
Requires-Python: >=3.6
License-File: LICENSE
Requires-Dist: numpy
Requires-Dist: beautifulsoup4 (>=4.9)
Requires-Dist: requests (>=2.25)
Requires-Dist: astropy (>=4)
Requires-Dist: scipy (>=0.19)
